dpt_cli/__init__.py
dpt_cli/cli.py
dpt_cli-1.0.3.data/data/docs/LICENSE
dpt_cli-1.0.3.data/data/docs/README
dpt_cli-1.0.3.dist-info/LICENSE
dpt_cli-1.0.3.dist-info/METADATA
dpt_cli-1.0.3.dist-info/WHEEL
dpt_cli-1.0.3.dist-info/top_level.txt
dpt_cli-1.0.3.dist-info/RECORD
